prelude/__coconut__.py
prelude/__init__.py
prelude/main.py
prelude/main_test.py
prelude/typevars.py
prelude/util.py
prelude/util_test.py
coconut_prelude-0.2.6.dist-info/LICENSE
coconut_prelude-0.2.6.dist-info/METADATA
coconut_prelude-0.2.6.dist-info/WHEEL
coconut_prelude-0.2.6.dist-info/top_level.txt
coconut_prelude-0.2.6.dist-info/RECORD
