Metadata-Version: 2.1
Name: coconut-prelude
Version: 0.2.6
Summary: An implementation of Haskell's Prelude in Python using Coconut.
Home-page: https://github.com/evhub/coconut-prelude
Author: Evan Hubinger
Author-email: evanjhub@gmail.com
License-File: LICENSE
Requires-Dist: coconut[mypy]
Requires-Dist: typing ; python_version<'3.5'
Provides-Extra: dev
Requires-Dist: pytest ; extra == 'dev'
